mediapipe/__init__.py
mediapipe/version.txt
mediapipe/calculators/__init__.py
mediapipe/calculators/audio/__init__.py
mediapipe/calculators/audio/mfcc_mel_calculators_pb2.py
mediapipe/calculators/audio/rational_factor_resample_calculator_pb2.py
mediapipe/calculators/audio/resample_time_series_calculator_pb2.py
mediapipe/calculators/audio/spectrogram_calculator_pb2.py
mediapipe/calculators/audio/stabilized_log_calculator_pb2.py
mediapipe/calculators/audio/time_series_framer_calculator_pb2.py
mediapipe/calculators/core/__init__.py
mediapipe/calculators/core/bypass_calculator_pb2.py
mediapipe/calculators/core/clip_vector_size_calculator_pb2.py
mediapipe/calculators/core/concatenate_vector_calculator_pb2.py
mediapipe/calculators/core/constant_side_packet_calculator_pb2.py
mediapipe/calculators/core/dequantize_byte_array_calculator_pb2.py
mediapipe/calculators/core/flow_limiter_calculator_pb2.py
mediapipe/calculators/core/gate_calculator_pb2.py
mediapipe/calculators/core/get_vector_item_calculator_pb2.py
mediapipe/calculators/core/graph_profile_calculator_pb2.py
mediapipe/calculators/core/packet_cloner_calculator_pb2.py
mediapipe/calculators/core/packet_resampler_calculator_pb2.py
mediapipe/calculators/core/packet_thinner_calculator_pb2.py
mediapipe/calculators/core/quantize_float_vector_calculator_pb2.py
mediapipe/calculators/core/sequence_shift_calculator_pb2.py
mediapipe/calculators/core/split_vector_calculator_pb2.py
mediapipe/calculators/image/__init__.py
mediapipe/calculators/image/bilateral_filter_calculator_pb2.py
mediapipe/calculators/image/feature_detector_calculator_pb2.py
mediapipe/calculators/image/image_clone_calculator_pb2.py
mediapipe/calculators/image/image_cropping_calculator_pb2.py
mediapipe/calculators/image/image_transformation_calculator_pb2.py
mediapipe/calculators/image/mask_overlay_calculator_pb2.py
mediapipe/calculators/image/opencv_encoded_image_to_image_frame_calculator_pb2.py
mediapipe/calculators/image/opencv_image_encoder_calculator_pb2.py
mediapipe_numpy2-0.10.21.dist-info/LICENSE
mediapipe_numpy2-0.10.21.dist-info/METADATA
mediapipe_numpy2-0.10.21.dist-info/WHEEL
mediapipe_numpy2-0.10.21.dist-info/top_level.txt
mediapipe_numpy2-0.10.21.dist-info/RECORD
